pipeai/__init__.py
pipeai/version.py
pipeai/checkpoint/__init__.py
pipeai/checkpoint/checkpoint.py
pipeai/config/__init__.py
pipeai/config/config.py
pipeai/config/utils.py
pipeai/data/__init__.py
pipeai/data/dataset.py
pipeai/data/loader/__init__.py
pipeai/data/loader/builder.py
pipeai/data/loader/perfetcher.py
pipeai/device/__init__.py
pipeai/device/device.py
pipeai/dist/__init__.py
pipeai/dist/dist.py
pipeai/entry_point/__init__.py
pipeai/entry_point/easytrain.py
pipeai/evaluator/__init__.py
pipeai/evaluator/metric.py
pipeai/launcher/__init__.py
pipeai/launcher/launcher.py
pipeai/logging/__init__.py
pipeai/logging/logger.py
pipeai/model/__init__.py
pipeai/model/builder.py
pipeai/model/module.py
pipeai/optim/__init__.py
pipeai/optim/builder.py
pipeai/optim/custom/__init__.py
pipeai/optim/custom/lr_scheduler/__init__.py
pipeai/optim/custom/lr_scheduler/cosine_warmup_lr.py
pipeai/optim/custom/optim/__init__.py
pipeai/optim/custom/optim/lamb.py
pipeai/runner/__init__.py
pipeai/runner/runner.py
pipeai/utils/__init__.py
pipeai/utils/env.py
pipeai/utils/misc.py
pipeai/utils/timer.py
pipeai-0.0.6.dist-info/METADATA
pipeai-0.0.6.dist-info/WHEEL
pipeai-0.0.6.dist-info/entry_points.txt
pipeai-0.0.6.dist-info/licenses/LICENSE
pipeai-0.0.6.dist-info/RECORD
